evm_trace/__init__.py
evm_trace/base.py
evm_trace/display.py
evm_trace/enums.py
evm_trace/gas.py
evm_trace/geth.py
evm_trace/parity.py
evm_trace/py.typed
evm_trace/version.py
evm_trace/vmtrace.py
evm_trace-0.2.5.dist-info/licenses/LICENSE
evm_trace-0.2.5.dist-info/METADATA
evm_trace-0.2.5.dist-info/WHEEL
evm_trace-0.2.5.dist-info/top_level.txt
evm_trace-0.2.5.dist-info/RECORD
