Metadata-Version: 2.4
Name: evm-trace
Version: 0.2.5
Summary: evm-trace: Ethereum Virtual Machine transaction tracing tool
Home-page: https://github.com/ApeWorX/evm-trace
Author: ApeWorX Ltd.
Author-email: admin@apeworx.io
License: Apache-2.0
Keywords: ethereum
Classifier: Development Status :: 5 - Production/Stable
Classifier: Intended Audience :: Developers
Classifier: License :: OSI Approved :: Apache Software License
Classifier: Natural Language :: English
Classifier: Operating System :: MacOS
Classifier: Operating System :: POSIX
Classifier: Programming Language :: Python :: 3
Classifier: Programming Language :: Python :: 3.9
Classifier: Programming Language :: Python :: 3.10
Classifier: Programming Language :: Python :: 3.11
Classifier: Programming Language :: Python :: 3.12
Classifier: Programming Language :: Python :: 3.13
Requires-Python: >=3.9,<4
License-File: LICENSE
Requires-Dist: cchecksum<1,>=0.0.3
Requires-Dist: eth-pydantic-types<0.3,>=0.2.0
Requires-Dist: eth-utils<6,>=2.3.1
Requires-Dist: msgspec>=0.8
Requires-Dist: pydantic<3,>=2.5.2
Requires-Dist: py-evm<0.11,>=0.10.1b1
Provides-Extra: test
Requires-Dist: pytest>=6.0; extra == "test"
Requires-Dist: pytest-xdist; extra == "test"
Requires-Dist: pytest-cov; extra == "test"
Requires-Dist: hypothesis<7.0,>=6.2.0; extra == "test"
Requires-Dist: eth-hash[pysha3]; extra == "test"
Provides-Extra: lint
Requires-Dist: black<26,>=25.1.0; extra == "lint"
Requires-Dist: mypy<2,>=1.15.0; extra == "lint"
Requires-Dist: types-setuptools; extra == "lint"
Requires-Dist: flake8<8,>=7.2.0; extra == "lint"
Requires-Dist: flake8-breakpoint<2,>=1.1.0; extra == "lint"
Requires-Dist: flake8-print<5,>=4.0.1; extra == "lint"
Requires-Dist: flake8-pydantic; extra == "lint"
Requires-Dist: flake8-type-checking; extra == "lint"
Requires-Dist: isort<6,>=5.10.1; extra == "lint"
Requires-Dist: mdformat>=0.7.22; extra == "lint"
Requires-Dist: mdformat-gfm>=0.3.5; extra == "lint"
Requires-Dist: mdformat-frontmatter>=0.4.1; extra == "lint"
Requires-Dist: mdformat-pyproject>=0.0.2; extra == "lint"
Provides-Extra: release
Requires-Dist: setuptools>=75.6.0; extra == "release"
Requires-Dist: wheel; extra == "release"
Requires-Dist: twine; extra == "release"
Provides-Extra: dev
Requires-Dist: pytest>=6.0; extra == "dev"
Requires-Dist: pytest-xdist; extra == "dev"
Requires-Dist: pytest-cov; extra == "dev"
Requires-Dist: hypothesis<7.0,>=6.2.0; extra == "dev"
Requires-Dist: eth-hash[pysha3]; extra == "dev"
Requires-Dist: black<26,>=25.1.0; extra == "dev"
Requires-Dist: mypy<2,>=1.15.0; extra == "dev"
Requires-Dist: types-setuptools; extra == "dev"
Requires-Dist: flake8<8,>=7.2.0; extra == "dev"
Requires-Dist: flake8-breakpoint<2,>=1.1.0; extra == "dev"
Requires-Dist: flake8-print<5,>=4.0.1; extra == "dev"
Requires-Dist: flake8-pydantic; extra == "dev"
Requires-Dist: flake8-type-checking; extra == "dev"
Requires-Dist: isort<6,>=5.10.1; extra == "dev"
Requires-Dist: mdformat>=0.7.22; extra == "dev"
Requires-Dist: mdformat-gfm>=0.3.5; extra == "dev"
Requires-Dist: mdformat-frontmatter>=0.4.1; extra == "dev"
Requires-Dist: mdformat-pyproject>=0.0.2; extra == "dev"
Requires-Dist: setuptools>=75.6.0; extra == "dev"
Requires-Dist: wheel; extra == "dev"
Requires-Dist: twine; extra == "dev"
Requires-Dist: commitizen; extra == "dev"
Requires-Dist: pre-commit; extra == "dev"
Requires-Dist: pytest-watch; extra == "dev"
Requires-Dist: IPython; extra == "dev"
Requires-Dist: ipdb; extra == "dev"
Dynamic: author
Dynamic: author-email
Dynamic: classifier
Dynamic: description
Dynamic: description-content-type
Dynamic: home-page
Dynamic: keywords
Dynamic: license
Dynamic: license-file
Dynamic: provides-extra
Dynamic: requires-dist
Dynamic: requires-python
Dynamic: summary
